{
 "actions": [],
 "allow_rename": 1,
 "creation": "2024-09-20 11:11:07.509113",
 "default_view": "List",
 "doctype": "DocType",
 "editable_grid": 1,
 "engine": "InnoDB",
 "field_order": [
  "reference_doctype",
  "reference_name",
  "grand_total",
  "outstanding",
  "allocated_amount"
 ],
 "fields": [
  {
   "fieldname": "reference_name",
   "fieldtype": "Dynamic Link",
   "in_list_view": 1,
   "label": "Name",
   "options": "reference_doctype",
   "reqd": 1
  },
  {
   "fieldname": "reference_doctype",
   "fieldtype": "Link",
   "in_list_view": 1,
   "label": "Type",
   "options": "DocType",
   "reqd": 1
  },
  {
   "fieldname": "allocated_amount",
   "fieldtype": "Float",
   "in_list_view": 1,
   "label": "Allocated Amount",
   "reqd": 1
  },
  {
   "fieldname": "grand_total",
   "fieldtype": "Float",
   "label": "Grand Total ",
   "read_only": 1
  },
  {
   "fieldname": "outstanding",
   "fieldtype": "Float",
   "label": "Outstanding ",
   "read_only": 1
  }
 ],
 "index_web_pages_for_search": 1,
 "istable": 1,
 "links": [],
 "modified": "2024-09-26 09:51:27.194874",
 "modified_by": "Administrator",
 "module": "Abgc Reports",
 "name": "Payment Refrences",
 "owner": "Administrator",
 "permissions": [],
 "sort_field": "modified",
 "sort_order": "DESC",
 "states": []
}